pyod_pyspark/__init__.py
pyod_pyspark/core/__init__.py
pyod_pyspark/core/decorators.py
pyod_pyspark/core/filter.py
pyod_pyspark/core/format.py
pyod_pyspark/core/queries.py
pyod_pyspark/core/selectors.py
pyod_pyspark/core/summarize.py
pyod_pyspark/core/utils.py
pyod_pyspark/example/__init__.py
pyod_pyspark/example/classes.py
pyod_pyspark/experimental/__init__.py
pyod_pyspark/experimental/compose.py
pyod_pyspark/experimental/environment.py
pyod_pyspark/experimental/pyemail/__init__.py
pyod_pyspark/experimental/pyemail/filters.py
pyod_pyspark/experimental/pyemail/pyemail.py
pyod_pyspark/plugins/__init__.py
pyod_pyspark/tidy/__init__.py
pyod_pyspark/tidy/tidydataframe/TidyDataFrame.py
pyod_pyspark/tidy/tidyschema/cdm_transform.py
pyod_pyspark/tidy/tidyschema/cdm_validate.py
pyod_pyspark/tidy/tidyschema/datatypes.py
pyod_pyspark/tidy/tidyschema/models.py
pyod_pyspark/tidy/tidyworkflow/__init__.py
pyod_pyspark/tidy/tidyworkflow/tidyworkflow.py
pyod_pyspark-0.1.0.dist-info/METADATA
pyod_pyspark-0.1.0.dist-info/WHEEL
pyod_pyspark-0.1.0.dist-info/RECORD
