Metadata-Version: 2.1
Name: pyod-pyspark
Version: 0.1.0
Summary: 
License: MIT
Author: lucas-nelson-uiuc
Author-email: lucas.nelson.contacts@gmail.com
Requires-Python: >=3.10,<4.0
Classifier: License :: OSI Approved :: MIT License
Classifier: Programming Language :: Python :: 3
Classifier: Programming Language :: Python :: 3.10
Classifier: Programming Language :: Python :: 3.11
Classifier: Programming Language :: Python :: 3.12
Requires-Dist: attrs (>=23.2.0,<24.0.0)
Requires-Dist: docxtpl (>=0.17.0,<0.18.0)
Requires-Dist: jinja2 (>=3.1.3,<4.0.0)
Requires-Dist: loguru (>=0.7.2,<0.8.0)
Requires-Dist: pyspark (==3.3.2)
